wii_roms_tool/__init__.py
wii_roms_tool/src/__init__.py
wii_roms_tool/src/common.py
wii_roms_tool/src/downloads.py
wii_roms_tool/src/main.py
wii_roms_tool/src/extractors/search_romsfun.py
wii_roms_tool/src/extractors/search_vimms.py
wii_roms_tool-0.6.dist-info/METADATA
wii_roms_tool-0.6.dist-info/WHEEL
wii_roms_tool-0.6.dist-info/entry_points.txt
wii_roms_tool-0.6.dist-info/licenses/LICENSE
wii_roms_tool-0.6.dist-info/RECORD
