Metadata-Version: 2.4
Name: wii-roms-tool
Version: 0.6
Summary: A tool for automatically downloading wii roms
Project-URL: Homepage, https://github.com/Tmaster055/Wii-Rom-Downloader
Project-URL: Issues, https://github.com/Tmaster055/Wii-Rom-Downloader/issues
Author: Tmaster055
License-File: LICENSE
Classifier: License :: OSI Approved :: MIT License
Classifier: Operating System :: OS Independent
Classifier: Programming Language :: Python :: 3
Requires-Python: >=3.8
Requires-Dist: bs4
Requires-Dist: cloudscraper
Requires-Dist: playwright
Requires-Dist: py7zr
Requires-Dist: requests
Requires-Dist: tqdm
Requires-Dist: windows-curses; platform_system == 'Windows'
